<annotation>
	<folder>images</folder>
	<filename>00000181.xml</filename>
	<path>L:/Dataset/Mine/Plants/pepper_teach\resized/labels/00000181.xml00000181.xml</path>
	<source>
		<database>Unknown</database>
	</source>
	<size>
		<width>960</width>
		<height>640</height>
		<depth>3</depth>
	</size>
	<segmented>0</segmented>
	<object>
		<name>fruit</name>
		<pose>Unspecified</pose>
		<truncated>0</truncated>
		<difficult>0</difficult>
		<bndbox>
			<xmin>385</xmin>
			<ymin>217</ymin>
			<xmax>535</xmax>
			<ymax>400</ymax>
		</bndbox>
	</object>
	<object>
		<name>fruit</name>
		<pose>Unspecified</pose>
		<truncated>0</truncated>
		<difficult>0</difficult>
		<bndbox>
			<xmin>327</xmin>
			<ymin>342</ymin>
			<xmax>431</xmax>
			<ymax>497</ymax>
		</bndbox>
	</object>
	<object>
		<name>fruit</name>
		<pose>Unspecified</pose>
		<truncated>0</truncated>
		<difficult>0</difficult>
		<bndbox>
			<xmin>448</xmin>
			<ymin>367</ymin>
			<xmax>544</xmax>
			<ymax>480</ymax>
		</bndbox>
	</object>
	<object>
		<name>fruit</name>
		<pose>Unspecified</pose>
		<truncated>0</truncated>
		<difficult>0</difficult>
		<bndbox>
			<xmin>537</xmin>
			<ymin>253</ymin>
			<xmax>637</xmax>
			<ymax>402</ymax>
		</bndbox>
	</object>
	<object>
		<name>fruit</name>
		<pose>Unspecified</pose>
		<truncated>0</truncated>
		<difficult>0</difficult>
		<bndbox>
			<xmin>757</xmin>
			<ymin>441</ymin>
			<xmax>903</xmax>
			<ymax>608</ymax>
		</bndbox>
	</object>
	<object>
		<name>pedicle</name>
		<pose>Unspecified</pose>
		<truncated>0</truncated>
		<difficult>0</difficult>
		<bndbox>
			<xmin>780</xmin>
			<ymin>452</ymin>
			<xmax>828</xmax>
			<ymax>472</ymax>
		</bndbox>
	</object>
	<object>
		<name>fruit</name>
		<pose>Unspecified</pose>
		<truncated>0</truncated>
		<difficult>0</difficult>
		<bndbox>
			<xmin>504</xmin>
			<ymin>2</ymin>
			<xmax>696</xmax>
			<ymax>122</ymax>
		</bndbox>
	</object>
	<object>
		<name>immature</name>
		<pose>Unspecified</pose>
		<truncated>0</truncated>
		<difficult>0</difficult>
		<bndbox>
			<xmin>249</xmin>
			<ymin>508</ymin>
			<xmax>293</xmax>
			<ymax>556</ymax>
		</bndbox>
	</object>
	
</annotation>	