<annotation>
	<folder>images</folder>
	<filename>00000187.xml</filename>
	<path>L:/Dataset/Mine/Plants/pepper_teach\resized/labels/00000187.xml00000187.xml</path>
	<source>
		<database>Unknown</database>
	</source>
	<size>
		<width>960</width>
		<height>640</height>
		<depth>3</depth>
	</size>
	<segmented>0</segmented>
	<object>
		<name>fruit</name>
		<pose>Unspecified</pose>
		<truncated>0</truncated>
		<difficult>0</difficult>
		<bndbox>
			<xmin>392</xmin>
			<ymin>336</ymin>
			<xmax>504</xmax>
			<ymax>499</ymax>
		</bndbox>
	</object>
	<object>
		<name>fruit</name>
		<pose>Unspecified</pose>
		<truncated>0</truncated>
		<difficult>0</difficult>
		<bndbox>
			<xmin>365</xmin>
			<ymin>433</ymin>
			<xmax>450</xmax>
			<ymax>560</ymax>
		</bndbox>
	</object>
	<object>
		<name>fruit</name>
		<pose>Unspecified</pose>
		<truncated>0</truncated>
		<difficult>0</difficult>
		<bndbox>
			<xmin>482</xmin>
			<ymin>383</ymin>
			<xmax>575</xmax>
			<ymax>542</ymax>
		</bndbox>
	</object>
	<object>
		<name>fruit</name>
		<pose>Unspecified</pose>
		<truncated>0</truncated>
		<difficult>0</difficult>
		<bndbox>
			<xmin>447</xmin>
			<ymin>32</ymin>
			<xmax>600</xmax>
			<ymax>267</ymax>
		</bndbox>
	</object>
	<object>
		<name>fruit</name>
		<pose>Unspecified</pose>
		<truncated>0</truncated>
		<difficult>0</difficult>
		<bndbox>
			<xmin>803</xmin>
			<ymin>0</ymin>
			<xmax>898</xmax>
			<ymax>80</ymax>
		</bndbox>
	</object>
	
</annotation>	